censor/brokers.py
censor/caching.py
censor/censors.py
censor/clients.py
censor/command.py
censor/console.py
censor/excepts.py
censor/message.py
censor/objects.py
censor/parsing.py
censor/reactor.py
censor/storage.py
censor/threads.py
censor/utility.py
censor/modules/__init__.py
censor/modules/bsc.py
censor/modules/err.py
censor/modules/flt.py
censor/modules/irc.py
censor/modules/mod.py
censor/modules/req.py
censor/modules/rss.py
censor/modules/sts.py
censor/modules/thr.py
censor-5.data/data/share/censor/README.rst
censor-5.data/data/share/censor/censor.service
censor-5.data/data/share/censor/img/exclamation.jpg
censor-5.data/data/share/censor/img/genocide.jpg
censor-5.data/data/share/censor/img/skull3.png
censor-5.data/data/share/censor/img/verbatim2.png
censor-5.data/data/share/censor/img/wallpaper.png
censor-5.data/data/share/censor/pdf/EM_Ack_OTP-CR-117_19.pdf
censor-5.data/data/share/censor/pdf/EM_T04_OTP-CR-117_19.pdf
censor-5.data/data/share/censor/pdf/EM_T07_OTP-CR-117_19_001.pdf
censor-5.data/data/share/censor/pdf/Kamer.pdf
censor-5.data/data/share/censor/pdf/bevestigd.pdf
censor-5.data/data/share/censor/pdf/koning.jpg
censor-5.data/scripts/censor
censor-5.dist-info/METADATA
censor-5.dist-info/WHEEL
censor-5.dist-info/top_level.txt
censor-5.dist-info/zip-safe
censor-5.dist-info/RECORD
