Metadata-Version: 2.1
Name: censor
Version: 5
Summary: basis to prosecute
Author-email: Censor <pycensor@gmail.com>
License: Public Domain
Project-URL: home, https://pypi.org/project/censor
Project-URL: bugs, https://github.com/pycensor/censor/issues
Project-URL: source, https://github.com/pycensor/censor
Classifier: Development Status :: 3 - Alpha
Classifier: License :: Public Domain
Classifier: Operating System :: Unix
Classifier: Programming Language :: Python
Classifier: Topic :: Utilities
